{
  "new": 89,
  "conflicts": [
    {
      "slug": "khu-tim-truyen-cong-cong-aa72hzu261jVUeGY",
      "title": "KHU TÌM TRUYỆN CÔNG CỘNG",
      "old_source": "WIKI",
      "old_chapters": 0,
      "new_source": "WIKI",
      "new_chapters": 0,
      "full_data": {
        "slug": "khu-tim-truyen-cong-cong-aa72hzu261jVUeGY",
        "title": "KHU TÌM TRUYỆN CÔNG CỘNG",
        "author": "TÌM TRUYỆN",
        "category": "võng du, game thực tế ảo, niên thượng (công lớn tuổi hơn thụ, hình như lớn hơn khá nhiều, mình nhớ công tầm 30-40 còn thụ tầm 20 mấy không rõ nữa)",
        "views": "73k",
        "likes": "0",
        "chapters": 0,
        "book_status": "Full",
        "cover_url": "https://wikicv.net/photo/69aefa0354b8081a459e4520?o=1",
        "rating": "N/A",
        "url": "https://wikicv.net/truyen/khu-tim-truyen-cong-cong-aa72hzu261jVUeGY",
        "source": "WIKI"
      }
    }
  ]
}